glassesValidator/__init__.py
glassesValidator/version.py
glassesValidator/GUI/__init__.py
glassesValidator/GUI/_general_imgui.py
glassesValidator/GUI/_impl/__init__.py
glassesValidator/GUI/_impl/callbacks.py
glassesValidator/GUI/_impl/db.py
glassesValidator/GUI/_impl/globals.py
glassesValidator/GUI/_impl/gui.py
glassesValidator/GUI/_impl/imagehelper.py
glassesValidator/GUI/_impl/process_pool.py
glassesValidator/GUI/_impl/structs.py
glassesValidator/GUI/_impl/utils.py
glassesValidator/preprocess/__init__.py
glassesValidator/process/__init__.py
glassesValidator/process/b_codeMarkerInterval.py
glassesValidator/process/c_detectMarkers.py
glassesValidator/process/d_gazeToPlane.py
glassesValidator/process/e_classifyFixations.py
glassesValidator/process/f_assignFixations.py
glassesValidator/process/g_calculateDataQuality.py
glassesValidator/resources/__init__.py
glassesValidator/resources/icons/__init__.py
glassesValidator/resources/icons/icon.icns
glassesValidator/resources/icons/icon.ico
glassesValidator/resources/icons/icon.png
glassesValidator/utils/__init__.py
glassesValidator/utils/makeVideo.py
glassesvalidator-3.2.0.dist-info/licenses/LICENSE
glassesvalidator-3.2.0.dist-info/METADATA
glassesvalidator-3.2.0.dist-info/WHEEL
glassesvalidator-3.2.0.dist-info/entry_points.txt
glassesvalidator-3.2.0.dist-info/top_level.txt
glassesvalidator-3.2.0.dist-info/RECORD
