Metadata-Version: 2.4
Name: glassesValidator
Version: 3.2.0
Summary: Automatic determination of accuracy of wearable eye tracker recordings.
Home-page: https://github.com/dcnieho/glassesValidator
Author: Diederick Niehorster
Author-email: diederick_c.niehorster@humlab.lu.se
License: MIT License
Project-URL: Source Code, https://github.com/dcnieho/glassesValidator
Classifier: Programming Language :: Python :: 3.11
Classifier: License :: OSI Approved :: MIT License
Classifier: Operating System :: OS Independent
Requires-Python: >=3.10
License-File: LICENSE
Requires-Dist: glassesTools[GUI]~=1.23.1
Requires-Dist: aiosqlite
Requires-Dist: uvloop; sys_platform != "win32"
Requires-Dist: pyobjc-framework-Cocoa; sys_platform == "darwin"
Requires-Dist: pathvalidate
Requires-Dist: pebble
Dynamic: author
Dynamic: author-email
Dynamic: classifier
Dynamic: description
Dynamic: description-content-type
Dynamic: home-page
Dynamic: license
Dynamic: license-file
Dynamic: project-url
Dynamic: requires-dist
Dynamic: requires-python
Dynamic: summary
